contextcrunch_langchain/__init__.py
contextcrunch_langchain/compressor.py
contextcrunch_langchain/context_cruncher.py
contextcrunch_langchain-1.0.2.dist-info/METADATA
contextcrunch_langchain-1.0.2.dist-info/WHEEL
contextcrunch_langchain-1.0.2.dist-info/licenses/LICENSE
contextcrunch_langchain-1.0.2.dist-info/RECORD
