Metadata-Version: 2.1
Name: contextcrunch-langchain
Version: 1.0.2
Summary: LangChain Integration for ContextCrunch prompt compression.
Project-URL: Homepage, https://github.com/contextcrunch-ai/contextcrunch-langchain-python
Project-URL: Issues, https://github.com/contextcrunch-ai/contextcrunch-langchain-python/issues
Author-email: Matthew Kwiatkowski <matt@mkcodes.ca>
License-File: LICENSE
Classifier: License :: OSI Approved :: MIT License
Classifier: Operating System :: OS Independent
Classifier: Programming Language :: Python :: 3
Requires-Python: >=3.8
Requires-Dist: contextcrunch>=1.0.1
Requires-Dist: langchain>=0.0.354
